voai.py
voai-0.0.4.dist-info/LICENSE
voai-0.0.4.dist-info/METADATA
voai-0.0.4.dist-info/WHEEL
voai-0.0.4.dist-info/top_level.txt
voai-0.0.4.dist-info/RECORD
