Metadata-Version: 2.1
Name: voai
Version: 0.0.4
Summary: A tool designed for working with 🧑‍💻ChatGPT API🧑‍💻
Home-page: https://github.com/CURVoid/voai
Author: VOID
License: APACHE 2.0
Keywords: chatgpt,gpt,chat,voai,openai,ai
Classifier: Operating System :: OS Independent
Classifier: License :: OSI Approved :: Apache Software License
Classifier: Programming Language :: Python :: 3
License-File: LICENSE
Requires-Dist: requests (==2.22.0)
